numericvision/__init__.py
numericvision/__main__.py
numericvision/config.cfg
numericvision/contours.py
numericvision/images.py
numericvision-0.1.0.dist-info/LICENSE
numericvision-0.1.0.dist-info/METADATA
numericvision-0.1.0.dist-info/WHEEL
numericvision-0.1.0.dist-info/entry_points.txt
numericvision-0.1.0.dist-info/top_level.txt
numericvision-0.1.0.dist-info/RECORD
