Metadata-Version: 2.1
Name: numericvision
Version: 0.1.0
Summary: Detects numeric displays in images using OpenCV
Home-page: https://github.com/igorm/numericvision
Author: Igor Myroshnichenko
Author-email: imyroshnichenko@gmail.com
License: Apache-2.0
Platform: UNKNOWN
Classifier: Development Status :: 4 - Beta
Classifier: Intended Audience :: Developers
Classifier: Intended Audience :: Science/Research
Classifier: License :: OSI Approved :: Apache Software License
Classifier: Programming Language :: Python
Classifier: Programming Language :: Python :: 3
Classifier: Topic :: Scientific/Engineering :: Image Recognition
Requires-Dist: importlib-resources
Requires-Dist: scikit-image
